withcode/__init__.py
withcode-0.1.2.dist-info/LICENSE
withcode-0.1.2.dist-info/METADATA
withcode-0.1.2.dist-info/WHEEL
withcode-0.1.2.dist-info/top_level.txt
withcode-0.1.2.dist-info/RECORD
